{
  "pipeline" : {
    "inputs" : {
      "service_dir" : "ecs-static-website",
      "dockerfile" : "Dockerfile",
      "unit_test_command" : "echo 'add your unit test command here'",
      "environment_account_ids" : ""
    }
  },
  "service" : {
    "name" : "Phoenix",
    "repository_connection_arn" : "arn:aws:codestar-connections:us-west-2:327050202254:connection/81d59ea4-6c4d-40fd-be09-1bae99471e8c",
    "repository_id" : "u2655/container-apps",
    "branch_name" : "main"
  },
  "service_instances" : [ {
    "name" : "Phoenix-Dev",
    "inputs" : {
      "port" : 80,
      "desired_count" : 1,
      "task_size" : "x-small",
      "subnet_type" : "public",
      "loadbalancer_type" : "application",
      "image" : "public.ecr.aws/z9d2n7e1/nginx:1.21.0",
      "backendurl" : "backend-svc-inst.backend-svc.fargate-env.local:80"
    },
    "outputs" : {
      "ServiceUrl" : "https://tf-lb-2022093017160714700000000a-1578503210.us-west-2.elb.amazonaws.com"
    },
    "environment" : {
      "account_id" : "327050202254",
      "name" : "Dev",
      "outputs" : {
        "ClusterArn" : "arn:aws:ecs:us-west-2:327050202254:cluster/Dev-Cluster",
        "SnsTopicName" : "Dev-ping",
        "VpcId" : "vpc-08404ca75f141a764",
        "CloudMapNamespaceId" : "ns-lody2zyrdadnw4iv",
        "PublicSubnetOneId" : "subnet-0c7ca6a1c80aca4f5",
        "ServiceTaskDefExecutionRoleArn" : "arn:aws:iam::327050202254:role/service_task_definition_execution_role20220928231132920700000001",
        "SnsRegion" : "us-west-2",
        "PublicSubnetTwoId" : "subnet-0e454c472da9c8072",
        "ClusterName" : "Dev-Cluster",
        "SnsTopicArn" : "arn:aws:sns:us-west-2:327050202254:Dev-ping",
        "PrivateSubnetTwoId" : "subnet-0c6988babdf1bd48e",
        "PrivateSubnetOneId" : "subnet-0b9d15b3ca8897686"
      }
    }
  } ],
  "proton_tags" : {
    "proton:account" : "327050202254",
    "proton:template" : "arn:aws:proton:us-west-2:327050202254:service-template/load-balanced-fargate-svc",
    "proton:service" : "arn:aws:proton:us-west-2:327050202254:service/Phoenix"
  },
  "//" : "arn:aws:proton:us-west-2:327050202254:service/Phoenix/pipeline"
}